tornado_retry/__about__.py
tornado_retry/__init__.py
tornado_retry/backoff.py
tornado_retry/engine.py
tornado_retry/jitter.py
tornado_retry/log.py
tornado_retry/test/__init__.py
tornado_retry/test/test_retry.py
tornado_retry-1.0.0.dist-info/DESCRIPTION.rst
tornado_retry-1.0.0.dist-info/METADATA
tornado_retry-1.0.0.dist-info/RECORD
tornado_retry-1.0.0.dist-info/WHEEL
tornado_retry-1.0.0.dist-info/metadata.json
tornado_retry-1.0.0.dist-info/top_level.txt
