Metadata-Version: 2.0
Name: tornado-retry
Version: 1.0.0
Summary: Tornado based retry loop
Home-page: UNKNOWN
Author: Nick Joyce
Author-email: nick+tornado-retry@boxdesign.co.uk
License: UNKNOWN
Platform: UNKNOWN
Requires-Dist: tornado
